MANIFEST.in
README.md
setup.py
PyRDW.egg-info/PKG-INFO
PyRDW.egg-info/SOURCES.txt
PyRDW.egg-info/dependency_links.txt
PyRDW.egg-info/not-zip-safe
PyRDW.egg-info/top_level.txt
pyrdw/__init__.py
pyrdw/license_number.py
pyrdw/test.py