Metadata-Version: 1.1
Name: PyRDW
Version: 1.1
Summary: PyRDW gives a basic way of fetching licensenumber-data from the RDW, the dutch department of road transport.
Home-page: http://github.com/rense/pyrdw
Author: Rense VanderHoek
Author-email: vanderhoek@gmail.com
License: MIT
Platform: UNKNOWN
Classifier: Development Status :: 4 - Beta
Classifier: Intended Audience :: Developers
Classifier: License :: OSI Approved :: MIT License
Classifier: Natural Language :: Dutch
Classifier: Programming Language :: Python :: 2 :: Only
